deepnog/__init__.py
deepnog/client/__init__.py
deepnog/client/client.py
deepnog/config/deepnog_config.yml
deepnog/config/deepnog_custom_config.yml
deepnog/config/deepnog_default_config.yml
deepnog/data/__init__.py
deepnog/data/dataset.py
deepnog/data/split.py
deepnog/learning/__init__.py
deepnog/learning/inference.py
deepnog/learning/training.py
deepnog/models/__init__.py
deepnog/models/deepfam.py
deepnog/models/deepnog.py
deepnog/tests/__init__.py
deepnog/tests/utils.py
deepnog/utils/__init__.py
deepnog/utils/bio.py
deepnog/utils/config.py
deepnog/utils/imports.py
deepnog/utils/io_utils.py
deepnog/utils/logger.py
deepnog/utils/metrics.py
deepnog/utils/network.py
deepnog/utils/sync.py
deepnog-1.2.4.dist-info/licenses/LICENSE
deepnog-1.2.4.dist-info/METADATA
deepnog-1.2.4.dist-info/WHEEL
deepnog-1.2.4.dist-info/entry_points.txt
deepnog-1.2.4.dist-info/top_level.txt
deepnog-1.2.4.dist-info/RECORD
