Metadata-Version: 2.4
Name: deepnog
Version: 1.2.4
Summary: Deep learning tool for protein orthologous group assignment
Author-email: Roman Feldbauer <sci@feldbauer.org>
Project-URL: homepage, https://github.com/univieCUBE/deepnog
Project-URL: documentation, https://deepnog.readthedocs.io/en/latest/?badge=latest
Project-URL: source, https://github.com/univieCUBE/deepnog
Project-URL: tracker, https://github.com/univieCUBE/deepnog/issues
Keywords: deep-learning,neural-networks,bioinformatics,computational-biology,protein-families,orthologous-groups,orthology,eggnog
Classifier: Development Status :: 4 - Beta
Classifier: Environment :: Console
Classifier: Intended Audience :: Science/Research
Classifier: License :: OSI Approved :: BSD License
Classifier: Operating System :: POSIX :: Linux
Classifier: Operating System :: MacOS :: MacOS X
Classifier: Operating System :: Microsoft :: Windows
Classifier: Operating System :: OS Independent
Classifier: Programming Language :: Python :: 3
Classifier: Programming Language :: Python :: 3.7
Classifier: Programming Language :: Python :: 3.8
Classifier: Programming Language :: Python :: 3.9
Classifier: Programming Language :: Python :: 3.10
Classifier: Programming Language :: Python :: 3.11
Classifier: Programming Language :: Python :: 3.12
Classifier: Programming Language :: Python :: 3.13
Classifier: Topic :: Scientific/Engineering :: Artificial Intelligence
Requires-Python: >=3.7
License-File: LICENSE
Requires-Dist: numpy
Requires-Dist: pandas
Requires-Dist: scikit-learn
Requires-Dist: torch>=1.2
Requires-Dist: Biopython
Requires-Dist: PyYAML
Requires-Dist: tqdm
Requires-Dist: tensorboard
Provides-Extra: test
Requires-Dist: pytest; extra == "test"
Dynamic: license-file
